mahamat/__init__.py
mahamat/core.py
mahamat-0.3.1.dist-info/licenses/LICENSE
mahamat-0.3.1.dist-info/METADATA
mahamat-0.3.1.dist-info/WHEEL
mahamat-0.3.1.dist-info/top_level.txt
mahamat-0.3.1.dist-info/RECORD
