Metadata-Version: 2.4
Name: mahamat
Version: 0.3.1
Summary: Module Python avec une barre de progression moderne
Author: Mahamat
Requires-Python: >=3.7
License-File: LICENSE
Dynamic: license-file
